frontend_forms/__init__.py
frontend_forms/app_settings.py
frontend_forms/apps.py
frontend_forms/decorators.py
frontend_forms/forms.py
frontend_forms/urls.py
frontend_forms/utils.py
frontend_forms/views.py
frontend_forms/static/frontend_forms/css/frontend_forms.css
frontend_forms/static/frontend_forms/js/frontend_forms.js
frontend_forms/static/frontend_forms/js/frontend_forms.jsx
frontend_forms/static/frontend_forms/js/frontend_forms_vanilla.js
frontend_forms/templates/frontend_forms/base.html
frontend_forms/templates/frontend_forms/check_logged_in_failed.html
frontend_forms/templates/frontend_forms/check_logged_in_failed_inner.html
frontend_forms/templates/frontend_forms/dialogs.html
frontend_forms/templates/frontend_forms/generic_form.html
frontend_forms/templates/frontend_forms/generic_form2.html
frontend_forms/templates/frontend_forms/generic_form2_inner.html
frontend_forms/templates/frontend_forms/generic_form_inner.html
frontend_forms/templates/frontend_forms/login.html
frontend_forms/templates/frontend_forms/login_inner.html
frontend_forms/templates/frontend_forms/login_successful_message.html
frontend_forms/templates/frontend_forms/overlay.html
frontend_forms/templates/frontend_forms/render_form.html
frontend_forms/templates/frontend_forms/render_form_field.html
frontend_forms/templatetags/__init__.py
frontend_forms/templatetags/frontend_forms_tags.py
django_frontend_forms-0.3.3.dist-info/METADATA
django_frontend_forms-0.3.3.dist-info/SOURCES.txt.py
django_frontend_forms-0.3.3.dist-info/WHEEL
django_frontend_forms-0.3.3.dist-info/dependency_links.txt.py
django_frontend_forms-0.3.3.dist-info/top_level.txt
django_frontend_forms-0.3.3.dist-info/top_level.txt.py
django_frontend_forms-0.3.3.dist-info/RECORD
