Metadata-Version: 2.1
Name: django-frontend-forms
Version: 0.3.3
Summary: A Django helper app to add editing capabilities to the frontend using modal forms
Home-page: http://github.com/morlandi/django-frontend-forms
Author: Mario Orlandi
Author-email: morlandi@brainstorm.it
License: MIT
Platform: UNKNOWN
Classifier: Development Status :: 5 - Production/Stable
Classifier: Operating System :: OS Independent
Classifier: Programming Language :: Python
Classifier: Framework :: Django
Classifier: Framework :: Django :: 1.11
Classifier: Framework :: Django :: 2.2
Classifier: Framework :: Django :: 3.0
Classifier: Intended Audience :: Developers
Classifier: License :: OSI Approved :: BSD License
Classifier: Natural Language :: English
Classifier: Programming Language :: Python :: 3.7
